mbq/__init__.py
mbq/api_tools/__init__.py
mbq/api_tools/__version__.py
mbq/api_tools/exceptions.py
mbq/api_tools/fields.py
mbq/api_tools/pagination.py
mbq/api_tools/responses.py
mbq/api_tools/schema.py
mbq/api_tools/settings.py
mbq/api_tools/test.py
mbq/api_tools/utils.py
mbq/api_tools/views.py
tests/__init__.py
tests/settings.py
tests/test_fields.py
tests/test_integration.py
tests/test_pagination.py
tests/test_schema.py
tests/test_views.py
mbq.apitools-0.0.1.dist-info/LICENSE
mbq.apitools-0.0.1.dist-info/METADATA
mbq.apitools-0.0.1.dist-info/WHEEL
mbq.apitools-0.0.1.dist-info/top_level.txt
mbq.apitools-0.0.1.dist-info/RECORD
